wsgi_module
mod_wsgi-py27
apxs_config
