Metadata-Version: 1.0
Name: wsgi-module
Version: 4.0b2
Summary: Installer for Apache/mod_wsgi.
Home-page: UNKNOWN
Author: Graham Dumpleton
Author-email: Graham.Dumpleton@gmail.com
License: Apache
Platform: UNKNOWN
